eotransform_pandas/__init__.py
eotransform_pandas/_version.py
eotransform_pandas/filesystem/__init__.py
eotransform_pandas/filesystem/gather.py
eotransform_pandas/filesystem/naming/__init__.py
eotransform_pandas/filesystem/naming/geopathfinder_conventions.py
eotransform_pandas/transformers/__init__.py
eotransform_pandas/transformers/group_by_n.py
eotransform_pandas-1.1.2.dist-info/LICENSE
eotransform_pandas-1.1.2.dist-info/METADATA
eotransform_pandas-1.1.2.dist-info/WHEEL
eotransform_pandas-1.1.2.dist-info/top_level.txt
eotransform_pandas-1.1.2.dist-info/RECORD
